README.md
setup.cfg
setup.py
topsis_Gurpreet_Singh_101803019/__init__.py
topsis_Gurpreet_Singh_101803019/topsis.py
topsis_Gurpreet_Singh_101803019.egg-info/PKG-INFO
topsis_Gurpreet_Singh_101803019.egg-info/SOURCES.txt
topsis_Gurpreet_Singh_101803019.egg-info/dependency_links.txt
topsis_Gurpreet_Singh_101803019.egg-info/entry_points.txt
topsis_Gurpreet_Singh_101803019.egg-info/requires.txt
topsis_Gurpreet_Singh_101803019.egg-info/top_level.txt