Metadata-Version: 2.1
Name: topsis-Gurpreet-Singh-101803019
Version: 0.1
Summary: A Python package implementing TOPSIS technique.
Home-page: UNKNOWN
Author: Gurpreet Singh
Author-email: goravsinghc.gc@gmail.com
License: MIT
Platform: UNKNOWN
Classifier: License :: OSI Approved :: MIT License
Classifier: Programming Language :: Python :: 3
Classifier: Programming Language :: Python :: 3.7
